czmodel/__init__.py
czmodel/core/__init__.py
czmodel/core/convert.py
czmodel/core/legacy_model_metadata.py
czmodel/core/legacy_model_spec.py
czmodel/core/model_metadata.py
czmodel/core/model_spec.py
czmodel/core/util/__init__.py
czmodel/core/util/_extract_model.py
czmodel/core/util/argument_parsing.py
czmodel/core/util/base_convert.py
czmodel/core/util/color_generation.py
czmodel/core/util/common.py
czmodel/core/util/model_packing.py
czmodel/core/util/onnx_export.py
czmodel/pytorch/__init__.py
czmodel/pytorch/convert.py
czmodel/pytorch/legacy_model_spec.py
czmodel/pytorch/model_spec.py
czmodel/pytorch/util/__init__.py
czmodel/pytorch/util/torch_export.py
czmodel-6.1.1.dist-info/licenses/LICENSE.txt
czmodel-6.1.1.dist-info/licenses/NOTICE.txt
czmodel-6.1.1.dist-info/METADATA
czmodel-6.1.1.dist-info/WHEEL
czmodel-6.1.1.dist-info/entry_points.txt
czmodel-6.1.1.dist-info/top_level.txt
czmodel-6.1.1.dist-info/RECORD
