Metadata-Version: 2.4
Name: czmodel
Version: 6.1.1
Summary: A conversion tool for PyTorch or ONNX models to CZANN
Author: Sebastian Rhode
Author-email: sebastian.rhode@zeiss.com
Project-URL: ZEN AI Toolkit, https://www.zeiss.com/microscopy/en/products/software/zeiss-zen/ai-toolkit.html
Classifier: Development Status :: 5 - Production/Stable
Classifier: Topic :: Scientific/Engineering :: Artificial Intelligence
Classifier: Programming Language :: Python :: 3.10
Classifier: Programming Language :: Python :: 3.11
Classifier: Programming Language :: Python :: 3.12
Classifier: Programming Language :: Python :: 3.13
Classifier: License :: OSI Approved :: Apache Software License
Classifier: Operating System :: OS Independent
Requires-Python: >=3.10,<3.14
License-File: LICENSE.txt
License-File: NOTICE.txt
Requires-Dist: onnx
Requires-Dist: numpy
Requires-Dist: xmltodict
Requires-Dist: defusedxml
Provides-Extra: pytorch
Requires-Dist: onnx; extra == "pytorch"
Requires-Dist: numpy; extra == "pytorch"
Requires-Dist: xmltodict; extra == "pytorch"
Requires-Dist: defusedxml; extra == "pytorch"
Requires-Dist: torch<=2.7.1,>2; extra == "pytorch"
Dynamic: author
Dynamic: author-email
Dynamic: classifier
Dynamic: description
Dynamic: description-content-type
Dynamic: license-file
Dynamic: project-url
Dynamic: provides-extra
Dynamic: requires-dist
Dynamic: requires-python
Dynamic: summary
